[
  {
    "name": "CSDN",
    "icon": "/images/icon/csdn.png",
    "tip": "来看看我的 CSDN 吧",
    "url": "https://blog.csdn.net/m0_61588837?spm=1000.2115.3001.5343"
  },
  {
    "name": "Github",
    "icon": "/images/icon/github.png",
    "tip": "去 Github 看看",
    "url": "https://github.com/DavidingPlus"
  },
  {
    "name": "QQ",
    "icon": "/images/icon/qq.png",
    "tip": "2065666169",
    "url": ""
  },
  {
    "name": "Wechat",
    "icon": "/images/icon/wechat.png",
    "tip": "lzx_DavidingPlus",
    "url": ""
  },
  {
    "name": "Email",
    "icon": "/images/icon/email.png",
    "tip": "来封 Email",
    "url": "mailto:2065666169@qq.com"
  }
]